amazon_ad/__init__.py
amazon_ad/test.py
amazon_ad/api/__init__.py
amazon_ad/api/auth.py
amazon_ad/api/base.py
amazon_ad/api/profiles.py
amazon_ad/api/report.py
amazon_ad/api/sb/__init__.py
amazon_ad/api/sb/report.py
amazon_ad/api/sp/__init__.py
amazon_ad/api/sp/report.py
amazon_ad/client/__init__.py
amazon_ad/client/auth.py
amazon_ad/client/base.py
amazon_ad/client/service.py
amazon_ad/core/__init__.py
amazon_ad/core/consts.py
amazon_ad/core/exceptions.py
amazon_ad/core/utils/__init__.py
amazon_ad/core/utils/amazon.py
amazon_ad/core/utils/serialize.py
amazon_ad/core/utils/text.py
amazon_ad-0.0.1b9.dist-info/METADATA
amazon_ad-0.0.1b9.dist-info/WHEEL
amazon_ad-0.0.1b9.dist-info/top_level.txt
amazon_ad-0.0.1b9.dist-info/RECORD
