Metadata-Version: 2.1
Name: amazon-ad
Version: 0.0.1b9
Summary: Amazon Advertising SDK
Home-page: UNKNOWN
Author: joshzda
Author-email: joshzda@gmail.com
License: UNKNOWN
Platform: UNKNOWN
Requires-Python: >=3.6
Requires-Dist: arrow (==0.12.1)
Requires-Dist: certifi (==2018.10.15)
Requires-Dist: chardet (==3.0.4)
Requires-Dist: idna (==2.7)
Requires-Dist: ipython (==7.2.0)
Requires-Dist: python-dateutil (==2.7.5)
Requires-Dist: requests (==2.20.1)
Requires-Dist: six (==1.11.0)
Requires-Dist: urllib3 (==1.24.1)
Requires-Dist: wcwidth (==0.1.9)
